intsig_mcp_atlassian/__init__.py
intsig_mcp_atlassian/__main__.py
intsig_mcp_atlassian/exceptions.py
intsig_mcp_atlassian/confluence/__init__.py
intsig_mcp_atlassian/confluence/client.py
intsig_mcp_atlassian/confluence/comments.py
intsig_mcp_atlassian/confluence/config.py
intsig_mcp_atlassian/confluence/constants.py
intsig_mcp_atlassian/confluence/labels.py
intsig_mcp_atlassian/confluence/pages.py
intsig_mcp_atlassian/confluence/search.py
intsig_mcp_atlassian/confluence/spaces.py
intsig_mcp_atlassian/confluence/users.py
intsig_mcp_atlassian/confluence/utils.py
intsig_mcp_atlassian/confluence/v2_adapter.py
intsig_mcp_atlassian/jira/__init__.py
intsig_mcp_atlassian/jira/attachments.py
intsig_mcp_atlassian/jira/boards.py
intsig_mcp_atlassian/jira/client.py
intsig_mcp_atlassian/jira/comments.py
intsig_mcp_atlassian/jira/config.py
intsig_mcp_atlassian/jira/constants.py
intsig_mcp_atlassian/jira/epics.py
intsig_mcp_atlassian/jira/fields.py
intsig_mcp_atlassian/jira/formatting.py
intsig_mcp_atlassian/jira/issues.py
intsig_mcp_atlassian/jira/links.py
intsig_mcp_atlassian/jira/projects.py
intsig_mcp_atlassian/jira/protocols.py
intsig_mcp_atlassian/jira/search.py
intsig_mcp_atlassian/jira/sprints.py
intsig_mcp_atlassian/jira/transitions.py
intsig_mcp_atlassian/jira/users.py
intsig_mcp_atlassian/jira/worklog.py
intsig_mcp_atlassian/models/__init__.py
intsig_mcp_atlassian/models/base.py
intsig_mcp_atlassian/models/constants.py
intsig_mcp_atlassian/models/confluence/__init__.py
intsig_mcp_atlassian/models/confluence/comment.py
intsig_mcp_atlassian/models/confluence/common.py
intsig_mcp_atlassian/models/confluence/label.py
intsig_mcp_atlassian/models/confluence/page.py
intsig_mcp_atlassian/models/confluence/search.py
intsig_mcp_atlassian/models/confluence/space.py
intsig_mcp_atlassian/models/confluence/user_search.py
intsig_mcp_atlassian/models/jira/__init__.py
intsig_mcp_atlassian/models/jira/agile.py
intsig_mcp_atlassian/models/jira/comment.py
intsig_mcp_atlassian-0.2.0.dist-info/METADATA
intsig_mcp_atlassian-0.2.0.dist-info/WHEEL
intsig_mcp_atlassian-0.2.0.dist-info/entry_points.txt
intsig_mcp_atlassian-0.2.0.dist-info/licenses/LICENSE
intsig_mcp_atlassian-0.2.0.dist-info/RECORD
